{
  "cutLines": [
    {
      "cutCount": 37,
      "cutScore": "+4"
    }
  ],
  "lastUpdated": "2026-04-12T14:06:59.001000",
  "leaderboardRows": [
    {
      "courseId": "014",
      "currentHole": 1,
      "currentRound": 4,
      "currentRoundScore": "",
      "firstName": "Cameron",
      "isAmateur": false,
      "lastName": "Young",
      "playerId": "57366",
      "position": "T1",
      "roundComplete": false,
      "rounds": [
        {
          "courseId": "014",
          "courseName": "Augusta National Golf Club",
          "roundId": 1,
          "scoreToPar": "+1",
          "strokes": 73
        },
        {
          "courseId": "014",
          "courseName": "Augusta National Golf Club",
          "roundId": 2,
          "scoreToPar": "-5",
          "strokes": 67
        },
        {
          "courseId": "014",
          "courseName": "Augusta National Golf Club",
          "roundId": 3,
          "scoreToPar": "-7",
          "strokes": 65
        }
      ],
      "startingHole": 1,
      "status": "not started",
      "teeTime": "2:25pm",
      "teeTimeTimestamp": "2026-04-12T18:25:00",
      "thru": "",
      "total": "-11",
      "totalStrokesFromCompletedRounds": "205"
    },
    {
      "courseId": "014",
      "currentHole": 1,
      "currentRound": 4,
      "currentRoundScore": "",
      "firstName": "Rory",
      "isAmateur": false,
      "lastName": "McIlroy",
      "playerId": "28237",
      "position": "T1",
      "roundComplete": false,
      "rounds": [
        {
          "courseId": "014",
          "courseName": "Augusta National Golf Club",
          "roundId": 1,
          "scoreToPar": "-5",
          "strokes": 67
        },
        {
          "courseId": "014",
          "courseName": "Augusta National Golf Club",
          "roundId": 2,
          "scoreToPar": "-7",
          "strokes": 65
        },
        {
          "courseId": "014",
          "courseName": "Augusta National Golf Club",
          "roundId": 3,
          "scoreToPar": "+1",
          "strokes": 73
        }
      ],
      "startingHole": 1,
      "status": "not started",
      "teeTime": "2:25pm",
      "teeTimeTimestamp": "2026-04-12T18:25:00",
      "thru": "",
      "total": "-11",
      "totalStrokesFromCompletedRounds": "205"
    },
    {
      "courseId": "014",
      "currentHole": 1,
      "currentRound": 4,
      "currentRoundScore": "",
      "firstName": "Sam",
      "isAmateur": false,
      "lastName": "Burns",
      "playerId": "47504",
      "position": "3",
      "roundComplete": false,
      "rounds": [
        {
          "courseId": "014",
          "courseName": "Augusta National Golf Club",
          "roundId": 1,
          "scoreToPar": "-5",
          "strokes": 67
        },
        {
          "courseId": "014",
          "courseName": "Augusta National Golf Club",
          "roundId": 2,
          "scoreToPar": "-1",
          "strokes": 71
        },
        {
          "courseId": "014",
          "courseName": "Augusta National Golf Club",
          "roundId": 3,
          "scoreToPar": "-4",
          "strokes": 68
        }
      ],
      "startingHole": 1,
      "status": "not started",
      "teeTime": "2:14pm",
      "teeTimeTimestamp": "2026-04-12T18:14:00",
      "thru": "",
      "total": "-10",
      "totalStrokesFromCompletedRounds": "206"
    },
    {
      "courseId": "014",
      "currentHole": 1,
      "currentRound": 4,
      "currentRoundScore": "",
      "firstName": "Shane",
      "isAmateur": false,
      "lastName": "Lowry",
      "playerId": "33204",
      "position": "4",
      "roundComplete": false,
      "rounds": [
        {
          "courseId": "014",
          "courseName": "Augusta National Golf Club",
          "roundId": 1,
          "scoreToPar": "-2",
          "strokes": 70
        },
        {
          "courseId": "014",
          "courseName": "Augusta National Golf Club",
          "roundId": 2,
          "scoreToPar": "-3",
          "strokes": 69
        },
        {
          "courseId": "014",
          "courseName": "Augusta National Golf Club",
          "roundId": 3,
          "scoreToPar": "-4",
          "strokes": 68
        }
      ],
      "startingHole": 1,
      "status": "not started",
      "teeTime": "2:14pm",
      "teeTimeTimestamp": "2026-04-12T18:14:00",
      "thru": "",
      "total": "-9",
      "totalStrokesFromCompletedRounds": "207"
    },
    {
      "courseId": "014",
      "currentHole": 1,
      "currentRound": 4,
      "currentRoundScore": "",
      "firstName": "Jason",
      "isAmateur": false,
      "lastName": "Day",
      "playerId": "28089",
      "position": "T5",
      "roundComplete": false,
      "rounds": [
        {
          "courseId": "014",
          "courseName": "Augusta National Golf Club",
          "roundId": 1,
          "scoreToPar": "-3",
          "strokes": 69
        },
        {
          "courseId": "014",
          "courseName": "Augusta National Golf Club",
          "roundId": 2,
          "scoreToPar": "-1",
          "strokes": 71
        },
        {
          "courseId": "014",
          "courseName": "Augusta National Golf Club",
          "roundId": 3,
          "scoreToPar": "-4",
          "strokes": 68
        }
      ],
      "startingHole": 1,
      "status": "not started",
      "teeTime": "2:03pm",
      "teeTimeTimestamp": "2026-04-12T18:03:00",
      "thru": "",
      "total": "-8",
      "totalStrokesFromCompletedRounds": "208"
    },
    {
      "courseId": "014",
      "currentHole": 1,
      "currentRound": 4,
      "currentRoundScore": "",
      "firstName": "Justin",
      "isAmateur": false,
      "lastName": "Rose",
      "playerId": "22405",
      "position": "T5",
      "roundComplete": false,
      "rounds": [
        {
          "courseId": "014",
          "courseName": "Augusta National Golf Club",
          "roundId": 1,
          "scoreToPar": "-2",
          "strokes": 70
        },
        {
          "courseId": "014",
          "courseName": "Augusta National Golf Club",
          "roundId": 2,
          "scoreToPar": "-3",
          "strokes": 69
        },
        {
          "courseId": "014",
          "courseName": "Augusta National Golf Club",
          "roundId": 3,
          "scoreToPar": "-3",
          "strokes": 69
        }
      ],
      "startingHole": 1,
      "status": "not started",
      "teeTime": "2:03pm",
      "teeTimeTimestamp": "2026-04-12T18:03:00",
      "thru": "",
      "total": "-8",
      "totalStrokesFromCompletedRounds": "208"
    },
    {
      "courseId": "014",
      "currentHole": 1,
      "currentRound": 4,
      "currentRoundScore": "",
      "firstName": "Scottie",
      "isAmateur": false,
      "lastName": "Scheffler",
      "playerId": "46046",
      "position": "T7",
      "roundComplete": false,
      "rounds": [
        {
          "courseId": "014",
          "courseName": "Augusta National Golf Club",
          "roundId": 1,
          "scoreToPar": "-2",
          "strokes": 70
        },
        {
          "courseId": "014",
          "courseName": "Augusta National Golf Club",
          "roundId": 2,
          "scoreToPar": "+2",
          "strokes": 74
        },
        {
          "courseId": "014",
          "courseName": "Augusta National Golf Club",
          "roundId": 3,
          "scoreToPar": "-7",
          "strokes": 65
        }
      ],
      "startingHole": 1,
      "status": "not started",
      "teeTime": "1:52pm",
      "teeTimeTimestamp": "2026-04-12T17:52:00",
      "thru": "",
      "total": "-7",
      "totalStrokesFromCompletedRounds": "209"
    },
    {
      "courseId": "014",
      "currentHole": 1,
      "currentRound": 4,
      "currentRoundScore": "",
      "firstName": "Haotong",
      "isAmateur": false,
      "lastName": "Li",
      "playerId": "35296",
      "position": "T7",
      "roundComplete": false,
      "rounds": [
        {
          "courseId": "014",
          "courseName": "Augusta National Golf Club",
          "roundId": 1,
          "scoreToPar": "-1",
          "strokes": 71
        },
        {
          "courseId": "014",
          "courseName": "Augusta National Golf Club",
          "roundId": 2,
          "scoreToPar": "-3",
          "strokes": 69
        },
        {
          "courseId": "014",
          "courseName": "Augusta National Golf Club",
          "roundId": 3,
          "scoreToPar": "-3",
          "strokes": 69
        }
      ],
      "startingHole": 1,
      "status": "not started",
      "teeTime": "1:52pm",
      "teeTimeTimestamp": "2026-04-12T17:52:00",
      "thru": "",
      "total": "-7",
      "totalStrokesFromCompletedRounds": "209"
    },
    {
      "courseId": "014",
      "currentHole": 1,
      "currentRound": 4,
      "currentRoundScore": "",
      "firstName": "Patrick",
      "isAmateur": false,
      "lastName": "Cantlay",
      "playerId": "35450",
      "position": "T9",
      "roundComplete": false,
      "rounds": [
        {
          "courseId": "014",
          "courseName": "Augusta National Golf Club",
          "roundId": 1,
          "scoreToPar": "+5",
          "strokes": 77
        },
        {
          "courseId": "014",
          "courseName": "Augusta National Golf Club",
          "roundId": 2,
          "scoreToPar": "-5",
          "strokes": 67
        },
        {
          "courseId": "014",
          "courseName": "Augusta National Golf Club",
          "roundId": 3,
          "scoreToPar": "-6",
          "strokes": 66
        }
      ],
      "startingHole": 1,
      "status": "not started",
      "teeTime": "1:41pm",
      "teeTimeTimestamp": "2026-04-12T17:41:00",
      "thru": "",
      "total": "-6",
      "totalStrokesFromCompletedRounds": "210"
    },
    {
      "courseId": "014",
      "currentHole": 1,
      "currentRound": 4,
      "currentRoundScore": "",
      "firstName": "Russell",
      "isAmateur": false,
      "lastName": "Henley",
      "playerId": "34098",
      "position": "T9",
      "roundComplete": false,
      "rounds": [
        {
          "courseId": "014",
          "courseName": "Augusta National Golf Club",
          "roundId": 1,
          "scoreToPar": "+1",
          "strokes": 73
        },
        {
          "courseId": "014",
          "courseName": "Augusta National Golf Club",
          "roundId": 2,
          "scoreToPar": "-1",
          "strokes": 71
        },
        {
          "courseId": "014",
          "courseName": "Augusta National Golf Club",
          "roundId": 3,
          "scoreToPar": "-6",
          "strokes": 66
        }
      ],
      "startingHole": 1,
      "status": "not started",
      "teeTime": "1:41pm",
      "teeTimeTimestamp": "2026-04-12T17:41:00",
      "thru": "",
      "total": "-6",
      "totalStrokesFromCompletedRounds": "210"
    },
    {
      "courseId": "014",
      "currentHole": 1,
      "currentRound": 4,
      "currentRoundScore": "",
      "firstName": "Patrick",
      "isAmateur": false,
      "lastName": "Reed",
      "playerId": "34360",
      "position": "T9",
      "roundComplete": false,
      "rounds": [
        {
          "courseId": "014",
          "courseName": "Augusta National Golf Club",
          "roundId": 1,
          "scoreToPar": "-3",
          "strokes": 69
        },
        {
          "courseId": "014",
          "courseName": "Augusta National Golf Club",
          "roundId": 2,
          "scoreToPar": "-3",
          "strokes": 69
        },
        {
          "courseId": "014",
          "courseName": "Augusta National Golf Club",
          "roundId": 3,
          "scoreToPar": "E",
          "strokes": 72
        }
      ],
      "startingHole": 1,
      "status": "not started",
      "teeTime": "1:30pm",
      "teeTimeTimestamp": "2026-04-12T17:30:00",
      "thru": "",
      "total": "-6",
      "totalStrokesFromCompletedRounds": "210"
    },
    {
      "courseId": "014",
      "currentHole": 1,
      "currentRound": 4,
      "currentRoundScore": "",
      "firstName": "Collin",
      "isAmateur": false,
      "lastName": "Morikawa",
      "playerId": "50525",
      "position": "T12",
      "roundComplete": false,
      "rounds": [
        {
          "courseId": "014",
          "courseName": "Augusta National Golf Club",
          "roundId": 1,
          "scoreToPar": "+2",
          "strokes": 74
        },
        {
          "courseId": "014",
          "courseName": "Augusta National Golf Club",
          "roundId": 2,
          "scoreToPar": "-3",
          "strokes": 69
        },
        {
          "courseId": "014",
          "courseName": "Augusta National Golf Club",
          "roundId": 3,
          "scoreToPar": "-4",
          "strokes": 68
        }
      ],
      "startingHole": 1,
      "status": "not started",
      "teeTime": "1:30pm",
      "teeTimeTimestamp": "2026-04-12T17:30:00",
      "thru": "",
      "total": "-5",
      "totalStrokesFromCompletedRounds": "211"
    },
    {
      "courseId": "014",
      "currentHole": 1,
      "currentRound": 4,
      "currentRoundScore": "",
      "firstName": "Jake",
      "isAmateur": false,
      "lastName": "Knapp",
      "playerId": "47420",
      "position": "T12",
      "roundComplete": false,
      "rounds": [
        {
          "courseId": "014",
          "courseName": "Augusta National Golf Club",
          "roundId": 1,
          "scoreToPar": "+1",
          "strokes": 73
        },
        {
          "courseId": "014",
          "courseName": "Augusta National Golf Club",
          "roundId": 2,
          "scoreToPar": "-3",
          "strokes": 69
        },
        {
          "courseId": "014",
          "courseName": "Augusta National Golf Club",
          "roundId": 3,
          "scoreToPar": "-3",
          "strokes": 69
        }
      ],
      "startingHole": 1,
      "status": "not started",
      "teeTime": "1:08pm",
      "teeTimeTimestamp": "2026-04-12T17:08:00",
      "thru": "",
      "total": "-5",
      "totalStrokesFromCompletedRounds": "211"
    },
    {
      "courseId": "014",
      "currentHole": 1,
      "currentRound": 4,
      "currentRoundScore": "",
      "firstName": "Ben",
      "isAmateur": false,
      "lastName": "Griffin",
      "playerId": "54591",
      "position": "T12",
      "roundComplete": false,
      "rounds": [
        {
          "courseId": "014",
          "courseName": "Augusta National Golf Club",
          "roundId": 1,
          "scoreToPar": "E",
          "strokes": 72
        },
        {
          "courseId": "014",
          "courseName": "Augusta National Golf Club",
          "roundId": 2,
          "scoreToPar": "-3",
          "strokes": 69
        },
        {
          "courseId": "014",
          "courseName": "Augusta National Golf Club",
          "roundId": 3,
          "scoreToPar": "-2",
          "strokes": 70
        }
      ],
      "startingHole": 1,
      "status": "not started",
      "teeTime": "1:08pm",
      "teeTimeTimestamp": "2026-04-12T17:08:00",
      "thru": "",
      "total": "-5",
      "totalStrokesFromCompletedRounds": "211"
    },
    {
      "courseId": "014",
      "currentHole": 1,
      "currentRound": 4,
      "currentRoundScore": "",
      "firstName": "Ryan",
      "isAmateur": false,
      "lastName": "Gerard",
      "playerId": "59018",
      "position": "T15",
      "roundComplete": false,
      "rounds": [
        {
          "courseId": "014",
          "courseName": "Augusta National Golf Club",
          "roundId": 1,
          "scoreToPar": "E",
          "strokes": 72
        },
        {
          "courseId": "014",
          "courseName": "Augusta National Golf Club",
          "roundId": 2,
          "scoreToPar": "E",
          "strokes": 72
        },
        {
          "courseId": "014",
          "courseName": "Augusta National Golf Club",
          "roundId": 3,
          "scoreToPar": "-4",
          "strokes": 68
        }
      ],
      "startingHole": 1,
      "status": "not started",
      "teeTime": "12:57pm",
      "teeTimeTimestamp": "2026-04-12T16:57:00",
      "thru": "",
      "total": "-4",
      "totalStrokesFromCompletedRounds": "212"
    },
    {
      "courseId": "014",
      "currentHole": 1,
      "currentRound": 4,
      "currentRoundScore": "",
      "firstName": "Xander",
      "isAmateur": false,
      "lastName": "Schauffele",
      "playerId": "48081",
      "position": "T15",
      "roundComplete": false,
      "rounds": [
        {
          "courseId": "014",
          "courseName": "Augusta National Golf Club",
          "roundId": 1,
          "scoreToPar": "-2",
          "strokes": 70
        },
        {
          "courseId": "014",
          "courseName": "Augusta National Golf Club",
          "roundId": 2,
          "scoreToPar": "E",
          "strokes": 72
        },
        {
          "courseId": "014",
          "courseName": "Augusta National Golf Club",
          "roundId": 3,
          "scoreToPar": "-2",
          "strokes": 70
        }
      ],
      "startingHole": 1,
      "status": "not started",
      "teeTime": "12:57pm",
      "teeTimeTimestamp": "2026-04-12T16:57:00",
      "thru": "",
      "total": "-4",
      "totalStrokesFromCompletedRounds": "212"
    },
    {
      "courseId": "014",
      "currentHole": 1,
      "currentRound": 4,
      "currentRoundScore": "",
      "firstName": "Brooks",
      "isAmateur": false,
      "lastName": "Koepka",
      "playerId": "36689",
      "position": "T15",
      "roundComplete": false,
      "rounds": [
        {
          "courseId": "014",
          "courseName": "Augusta National Golf Club",
          "roundId": 1,
          "scoreToPar": "E",
          "strokes": 72
        },
        {
          "courseId": "014",
          "courseName": "Augusta National Golf Club",
          "roundId": 2,
          "scoreToPar": "-3",
          "strokes": 69
        },
        {
          "courseId": "014",
          "courseName": "Augusta National Golf Club",
          "roundId": 3,
          "scoreToPar": "-1",
          "strokes": 71
        }
      ],
      "startingHole": 1,
      "status": "not started",
      "teeTime": "12:46pm",
      "teeTimeTimestamp": "2026-04-12T16:46:00",
      "thru": "",
      "total": "-4",
      "totalStrokesFromCompletedRounds": "212"
    },
    {
      "courseId": "014",
      "currentHole": 1,
      "currentRound": 4,
      "currentRoundScore": "",
      "firstName": "Wyndham",
      "isAmateur": false,
      "lastName": "Clark",
      "playerId": "51766",
      "position": "T15",
      "roundComplete": false,
      "rounds": [
        {
          "courseId": "014",
          "courseName": "Augusta National Golf Club",
          "roundId": 1,
          "scoreToPar": "E",
          "strokes": 72
        },
        {
          "courseId": "014",
          "courseName": "Augusta National Golf Club",
          "roundId": 2,
          "scoreToPar": "-4",
          "strokes": 68
        },
        {
          "courseId": "014",
          "courseName": "Augusta National Golf Club",
          "roundId": 3,
          "scoreToPar": "E",
          "strokes": 72
        }
      ],
      "startingHole": 1,
      "status": "not started",
      "teeTime": "12:46pm",
      "teeTimeTimestamp": "2026-04-12T16:46:00",
      "thru": "",
      "total": "-4",
      "totalStrokesFromCompletedRounds": "212"
    },
    {
      "courseId": "014",
      "currentHole": 1,
      "currentRound": 4,
      "currentRoundScore": "",
      "firstName": "Tyrrell",
      "isAmateur": false,
      "lastName": "Hatton",
      "playerId": "34363",
      "position": "T15",
      "roundComplete": false,
      "rounds": [
        {
          "courseId": "014",
          "courseName": "Augusta National Golf Club",
          "roundId": 1,
          "scoreToPar": "+2",
          "strokes": 74
        },
        {
          "courseId": "014",
          "courseName": "Augusta National Golf Club",
          "roundId": 2,
          "scoreToPar": "-6",
          "strokes": 66
        },
        {
          "courseId": "014",
          "courseName": "Augusta National Golf Club",
          "roundId": 3,
          "scoreToPar": "E",
          "strokes": 72
        }
      ],
      "startingHole": 1,
      "status": "not started",
      "teeTime": "12:35pm",
      "teeTimeTimestamp": "2026-04-12T16:35:00",
      "thru": "",
      "total": "-4",
      "totalStrokesFromCompletedRounds": "212"
    },
    {
      "courseId": "014",
      "currentHole": 1,
      "currentRound": 4,
      "currentRoundScore": "",
      "firstName": "Tommy",
      "isAmateur": false,
      "lastName": "Fleetwood",
      "playerId": "30911",
      "position": "T15",
      "roundComplete": false,
      "rounds": [
        {
          "courseId": "014",
          "courseName": "Augusta National Golf Club",
          "roundId": 1,
          "scoreToPar": "-1",
          "strokes": 71
        },
        {
          "courseId": "014",
          "courseName": "Augusta National Golf Club",
          "roundId": 2,
          "scoreToPar": "-4",
          "strokes": 68
        },
        {
          "courseId": "014",
          "courseName": "Augusta National Golf Club",
          "roundId": 3,
          "scoreToPar": "+1",
          "strokes": 73
        }
      ],
      "startingHole": 1,
      "status": "not started",
      "teeTime": "12:35pm",
      "teeTimeTimestamp": "2026-04-12T16:35:00",
      "thru": "",
      "total": "-4",
      "totalStrokesFromCompletedRounds": "212"
    },
    {
      "courseId": "014",
      "currentHole": 1,
      "currentRound": 4,
      "currentRoundScore": "",
      "firstName": "Ludvig",
      "isAmateur": false,
      "lastName": "Åberg",
      "playerId": "52955",
      "position": "T21",
      "roundComplete": false,
      "rounds": [
        {
          "courseId": "014",
          "courseName": "Augusta National Golf Club",
          "roundId": 1,
          "scoreToPar": "+2",
          "strokes": 74
        },
        {
          "courseId": "014",
          "courseName": "Augusta National Golf Club",
          "roundId": 2,
          "scoreToPar": "-2",
          "strokes": 70
        },
        {
          "courseId": "014",
          "courseName": "Augusta National Golf Club",
          "roundId": 3,
          "scoreToPar": "-3",
          "strokes": 69
        }
      ],
      "startingHole": 1,
      "status": "not started",
      "teeTime": "12:24pm",
      "teeTimeTimestamp": "2026-04-12T16:24:00",
      "thru": "",
      "total": "-3",
      "totalStrokesFromCompletedRounds": "213"
    },
    {
      "courseId": "014",
      "currentHole": 1,
      "currentRound": 4,
      "currentRoundScore": "",
      "firstName": "Brian",
      "isAmateur": false,
      "lastName": "Campbell",
      "playerId": "46443",
      "position": "T21",
      "roundComplete": false,
      "rounds": [
        {
          "courseId": "014",
          "courseName": "Augusta National Golf Club",
          "roundId": 1,
          "scoreToPar": "-1",
          "strokes": 71
        },
        {
          "courseId": "014",
          "courseName": "Augusta National Golf Club",
          "roundId": 2,
          "scoreToPar": "+1",
          "strokes": 73
        },
        {
          "courseId": "014",
          "courseName": "Augusta National Golf Club",
          "roundId": 3,
          "scoreToPar": "-3",
          "strokes": 69
        }
      ],
      "startingHole": 1,
      "status": "not started",
      "teeTime": "12:24pm",
      "teeTimeTimestamp": "2026-04-12T16:24:00",
      "thru": "",
      "total": "-3",
      "totalStrokesFromCompletedRounds": "213"
    },
    {
      "courseId": "014",
      "currentHole": 1,
      "currentRound": 4,
      "currentRoundScore": "",
      "firstName": "Nick",
      "isAmateur": false,
      "lastName": "Taylor",
      "playerId": "25493",
      "position": "T21",
      "roundComplete": false,
      "rounds": [
        {
          "courseId": "014",
          "courseName": "Augusta National Golf Club",
          "roundId": 1,
          "scoreToPar": "-1",
          "strokes": 71
        },
        {
          "courseId": "014",
          "courseName": "Augusta National Golf Club",
          "roundId": 2,
          "scoreToPar": "E",
          "strokes": 72
        },
        {
          "courseId": "014",
          "courseName": "Augusta National Golf Club",
          "roundId": 3,
          "scoreToPar": "-2",
          "strokes": 70
        }
      ],
      "startingHole": 1,
      "status": "not started",
      "teeTime": "12:13pm",
      "teeTimeTimestamp": "2026-04-12T16:13:00",
      "thru": "",
      "total": "-3",
      "totalStrokesFromCompletedRounds": "213"
    },
    {
      "courseId": "014",
      "currentHole": 1,
      "currentRound": 4,
      "currentRoundScore": "",
      "firstName": "Matt",
      "isAmateur": false,
      "lastName": "Fitzpatrick",
      "playerId": "40098",
      "position": "T21",
      "roundComplete": false,
      "rounds": [
        {
          "courseId": "014",
          "courseName": "Augusta National Golf Club",
          "roundId": 1,
          "scoreToPar": "+2",
          "strokes": 74
        },
        {
          "courseId": "014",
          "courseName": "Augusta National Golf Club",
          "roundId": 2,
          "scoreToPar": "-3",
          "strokes": 69
        },
        {
          "courseId": "014",
          "courseName": "Augusta National Golf Club",
          "roundId": 3,
          "scoreToPar": "-2",
          "strokes": 70
        }
      ],
      "startingHole": 1,
      "status": "not started",
      "teeTime": "12:13pm",
      "teeTimeTimestamp": "2026-04-12T16:13:00",
      "thru": "",
      "total": "-3",
      "totalStrokesFromCompletedRounds": "213"
    },
    {
      "courseId": "014",
      "currentHole": 1,
      "currentRound": 4,
      "currentRoundScore": "",
      "firstName": "Michael",
      "isAmateur": false,
      "lastName": "Brennan",
      "playerId": "61522",
      "position": "T21",
      "roundComplete": false,
      "rounds": [
        {
          "courseId": "014",
          "courseName": "Augusta National Golf Club",
          "roundId": 1,
          "scoreToPar": "E",
          "strokes": 72
        },
        {
          "courseId": "014",
          "courseName": "Augusta National Golf Club",
          "roundId": 2,
          "scoreToPar": "-1",
          "strokes": 71
        },
        {
          "courseId": "014",
          "courseName": "Augusta National Golf Club",
          "roundId": 3,
          "scoreToPar": "-2",
          "strokes": 70
        }
      ],
      "startingHole": 1,
      "status": "not started",
      "teeTime": "11:51am",
      "teeTimeTimestamp": "2026-04-12T15:51:00",
      "thru": "",
      "total": "-3",
      "totalStrokesFromCompletedRounds": "213"
    },
    {
      "courseId": "014",
      "currentHole": 1,
      "currentRound": 4,
      "currentRoundScore": "",
      "firstName": "Max",
      "isAmateur": false,
      "lastName": "Homa",
      "playerId": "39977",
      "position": "T21",
      "roundComplete": false,
      "rounds": [
        {
          "courseId": "014",
          "courseName": "Augusta National Golf Club",
          "roundId": 1,
          "scoreToPar": "E",
          "strokes": 72
        },
        {
          "courseId": "014",
          "courseName": "Augusta National Golf Club",
          "roundId": 2,
          "scoreToPar": "-2",
          "strokes": 70
        },
        {
          "courseId": "014",
          "courseName": "Augusta National Golf Club",
          "roundId": 3,
          "scoreToPar": "-1",
          "strokes": 71
        }
      ],
      "startingHole": 1,
      "status": "not started",
      "teeTime": "11:51am",
      "teeTimeTimestamp": "2026-04-12T15:51:00",
      "thru": "",
      "total": "-3",
      "totalStrokesFromCompletedRounds": "213"
    },
    {
      "courseId": "014",
      "currentHole": 1,
      "currentRound": 4,
      "currentRoundScore": "",
      "firstName": "Chris",
      "isAmateur": false,
      "lastName": "Gotterup",
      "playerId": "59095",
      "position": "T21",
      "roundComplete": false,
      "rounds": [
        {
          "courseId": "014",
          "courseName": "Augusta National Golf Club",
          "roundId": 1,
          "scoreToPar": "E",
          "strokes": 72
        },
        {
          "courseId": "014",
          "courseName": "Augusta National Golf Club",
          "roundId": 2,
          "scoreToPar": "-3",
          "strokes": 69
        },
        {
          "courseId": "014",
          "courseName": "Augusta National Golf Club",
          "roundId": 3,
          "scoreToPar": "E",
          "strokes": 72
        }
      ],
      "startingHole": 1,
      "status": "not started",
      "teeTime": "11:40am",
      "teeTimeTimestamp": "2026-04-12T15:40:00",
      "thru": "",
      "total": "-3",
      "totalStrokesFromCompletedRounds": "213"
    },
    {
      "courseId": "014",
      "currentHole": 1,
      "currentRound": 4,
      "currentRoundScore": "",
      "firstName": "Kristoffer",
      "isAmateur": false,
      "lastName": "Reitan",
      "playerId": "49855",
      "position": "T21",
      "roundComplete": false,
      "rounds": [
        {
          "courseId": "014",
          "courseName": "Augusta National Golf Club",
          "roundId": 1,
          "scoreToPar": "E",
          "strokes": 72
        },
        {
          "courseId": "014",
          "courseName": "Augusta National Golf Club",
          "roundId": 2,
          "scoreToPar": "-4",
          "strokes": 68
        },
        {
          "courseId": "014",
          "courseName": "Augusta National Golf Club",
          "roundId": 3,
          "scoreToPar": "+1",
          "strokes": 73
        }
      ],
      "startingHole": 1,
      "status": "not started",
      "teeTime": "11:40am",
      "teeTimeTimestamp": "2026-04-12T15:40:00",
      "thru": "",
      "total": "-3",
      "totalStrokesFromCompletedRounds": "213"
    },
    {
      "courseId": "014",
      "currentHole": 1,
      "currentRound": 4,
      "currentRoundScore": "",
      "firstName": "Sepp",
      "isAmateur": false,
      "lastName": "Straka",
      "playerId": "49960",
      "position": "T29",
      "roundComplete": false,
      "rounds": [
        {
          "courseId": "014",
          "courseName": "Augusta National Golf Club",
          "roundId": 1,
          "scoreToPar": "+1",
          "strokes": 73
        },
        {
          "courseId": "014",
          "courseName": "Augusta National Golf Club",
          "roundId": 2,
          "scoreToPar": "E",
          "strokes": 72
        },
        {
          "courseId": "014",
          "courseName": "Augusta National Golf Club",
          "roundId": 3,
          "scoreToPar": "-3",
          "strokes": 69
        }
      ],
      "startingHole": 1,
      "status": "not started",
      "teeTime": "11:29am",
      "teeTimeTimestamp": "2026-04-12T15:29:00",
      "thru": "",
      "total": "-2",
      "totalStrokesFromCompletedRounds": "214"
    },
    {
      "courseId": "014",
      "currentHole": 1,
      "currentRound": 4,
      "currentRoundScore": "",
      "firstName": "Jacob",
      "isAmateur": false,
      "lastName": "Bridgeman",
      "playerId": "60004",
      "position": "T29",
      "roundComplete": false,
      "rounds": [
        {
          "courseId": "014",
          "courseName": "Augusta National Golf Club",
          "roundId": 1,
          "scoreToPar": "-1",
          "strokes": 71
        },
        {
          "courseId": "014",
          "courseName": "Augusta National Golf Club",
          "roundId": 2,
          "scoreToPar": "+2",
          "strokes": 74
        },
        {
          "courseId": "014",
          "courseName": "Augusta National Golf Club",
          "roundId": 3,
          "scoreToPar": "-3",
          "strokes": 69
        }
      ],
      "startingHole": 1,
      "status": "not started",
      "teeTime": "11:29am",
      "teeTimeTimestamp": "2026-04-12T15:29:00",
      "thru": "",
      "total": "-2",
      "totalStrokesFromCompletedRounds": "214"
    },
    {
      "courseId": "014",
      "currentHole": 1,
      "currentRound": 4,
      "currentRoundScore": "",
      "firstName": "Sungjae",
      "isAmateur": false,
      "lastName": "Im",
      "playerId": "39971",
      "position": "T29",
      "roundComplete": false,
      "rounds": [
        {
          "courseId": "014",
          "courseName": "Augusta National Golf Club",
          "roundId": 1,
          "scoreToPar": "+4",
          "strokes": 76
        },
        {
          "courseId": "014",
          "courseName": "Augusta National Golf Club",
          "roundId": 2,
          "scoreToPar": "-3",
          "strokes": 69
        },
        {
          "courseId": "014",
          "courseName": "Augusta National Golf Club",
          "roundId": 3,
          "scoreToPar": "-3",
          "strokes": 69
        }
      ],
      "startingHole": 1,
      "status": "not started",
      "teeTime": "11:18am",
      "teeTimeTimestamp": "2026-04-12T15:18:00",
      "thru": "",
      "total": "-2",
      "totalStrokesFromCompletedRounds": "214"
    },
    {
      "courseId": "014",
      "currentHole": 1,
      "currentRound": 4,
      "currentRoundScore": "",
      "firstName": "Hideki",
      "isAmateur": false,
      "lastName": "Matsuyama",
      "playerId": "32839",
      "position": "T29",
      "roundComplete": false,
      "rounds": [
        {
          "courseId": "014",
          "courseName": "Augusta National Golf Club",
          "roundId": 1,
          "scoreToPar": "E",
          "strokes": 72
        },
        {
          "courseId": "014",
          "courseName": "Augusta National Golf Club",
          "roundId": 2,
          "scoreToPar": "-2",
          "strokes": 70
        },
        {
          "courseId": "014",
          "courseName": "Augusta National Golf Club",
          "roundId": 3,
          "scoreToPar": "E",
          "strokes": 72
        }
      ],
      "startingHole": 1,
      "status": "not started",
      "teeTime": "11:18am",
      "teeTimeTimestamp": "2026-04-12T15:18:00",
      "thru": "",
      "total": "-2",
      "totalStrokesFromCompletedRounds": "214"
    },
    {
      "courseId": "014",
      "currentHole": 1,
      "currentRound": 4,
      "currentRoundScore": "",
      "firstName": "Brian",
      "isAmateur": false,
      "lastName": "Harman",
      "playerId": "27644",
      "position": "T33",
      "roundComplete": false,
      "rounds": [
        {
          "courseId": "014",
          "courseName": "Augusta National Golf Club",
          "roundId": 1,
          "scoreToPar": "+7",
          "strokes": 79
        },
        {
          "courseId": "014",
          "courseName": "Augusta National Golf Club",
          "roundId": 2,
          "scoreToPar": "-3",
          "strokes": 69
        },
        {
          "courseId": "014",
          "courseName": "Augusta National Golf Club",
          "roundId": 3,
          "scoreToPar": "-5",
          "strokes": 67
        }
      ],
      "startingHole": 1,
      "status": "not started",
      "teeTime": "11:07am",
      "teeTimeTimestamp": "2026-04-12T15:07:00",
      "thru": "",
      "total": "-1",
      "totalStrokesFromCompletedRounds": "215"
    },
    {
      "courseId": "014",
      "currentHole": 1,
      "currentRound": 4,
      "currentRoundScore": "",
      "firstName": "Jordan",
      "isAmateur": false,
      "lastName": "Spieth",
      "playerId": "34046",
      "position": "T33",
      "roundComplete": false,
      "rounds": [
        {
          "courseId": "014",
          "courseName": "Augusta National Golf Club",
          "roundId": 1,
          "scoreToPar": "E",
          "strokes": 72
        },
        {
          "courseId": "014",
          "courseName": "Augusta National Golf Club",
          "roundId": 2,
          "scoreToPar": "+1",
          "strokes": 73
        },
        {
          "courseId": "014",
          "courseName": "Augusta National Golf Club",
          "roundId": 3,
          "scoreToPar": "-2",
          "strokes": 70
        }
      ],
      "startingHole": 1,
      "status": "not started",
      "teeTime": "11:07am",
      "teeTimeTimestamp": "2026-04-12T15:07:00",
      "thru": "",
      "total": "-1",
      "totalStrokesFromCompletedRounds": "215"
    },
    {
      "courseId": "014",
      "currentHole": 1,
      "currentRound": 4,
      "currentRoundScore": "",
      "firstName": "Harris",
      "isAmateur": false,
      "lastName": "English",
      "playerId": "34099",
      "position": "T33",
      "roundComplete": false,
      "rounds": [
        {
          "courseId": "014",
          "courseName": "Augusta National Golf Club",
          "roundId": 1,
          "scoreToPar": "+1",
          "strokes": 73
        },
        {
          "courseId": "014",
          "courseName": "Augusta National Golf Club",
          "roundId": 2,
          "scoreToPar": "-1",
          "strokes": 71
        },
        {
          "courseId": "014",
          "courseName": "Augusta National Golf Club",
          "roundId": 3,
          "scoreToPar": "-1",
          "strokes": 71
        }
      ],
      "startingHole": 1,
      "status": "not started",
      "teeTime": "10:56am",
      "teeTimeTimestamp": "2026-04-12T14:56:00",
      "thru": "",
      "total": "-1",
      "totalStrokesFromCompletedRounds": "215"
    },
    {
      "courseId": "014",
      "currentHole": 1,
      "currentRound": 4,
      "currentRoundScore": "",
      "firstName": "Samuel",
      "isAmateur": false,
      "lastName": "Stevens",
      "playerId": "55893",
      "position": "T36",
      "roundComplete": false,
      "rounds": [
        {
          "courseId": "014",
          "courseName": "Augusta National Golf Club",
          "roundId": 1,
          "scoreToPar": "E",
          "strokes": 72
        },
        {
          "courseId": "014",
          "courseName": "Augusta National Golf Club",
          "roundId": 2,
          "scoreToPar": "+2",
          "strokes": 74
        },
        {
          "courseId": "014",
          "courseName": "Augusta National Golf Club",
          "roundId": 3,
          "scoreToPar": "-2",
          "strokes": 70
        }
      ],
      "startingHole": 1,
      "status": "not started",
      "teeTime": "10:56am",
      "teeTimeTimestamp": "2026-04-12T14:56:00",
      "thru": "",
      "total": "E",
      "totalStrokesFromCompletedRounds": "216"
    },
    {
      "courseId": "014",
      "currentHole": 1,
      "currentRound": 4,
      "currentRoundScore": "",
      "firstName": "Adam",
      "isAmateur": false,
      "lastName": "Scott",
      "playerId": "24502",
      "position": "T36",
      "roundComplete": false,
      "rounds": [
        {
          "courseId": "014",
          "courseName": "Augusta National Golf Club",
          "roundId": 1,
          "scoreToPar": "E",
          "strokes": 72
        },
        {
          "courseId": "014",
          "courseName": "Augusta National Golf Club",
          "roundId": 2,
          "scoreToPar": "+2",
          "strokes": 74
        },
        {
          "courseId": "014",
          "courseName": "Augusta National Golf Club",
          "roundId": 3,
          "scoreToPar": "-2",
          "strokes": 70
        }
      ],
      "startingHole": 1,
      "status": "not started",
      "teeTime": "10:45am",
      "teeTimeTimestamp": "2026-04-12T14:45:00",
      "thru": "",
      "total": "E",
      "totalStrokesFromCompletedRounds": "216"
    },
    {
      "courseId": "014",
      "currentHole": 1,
      "currentRound": 4,
      "currentRoundScore": "",
      "firstName": "Marco",
      "isAmateur": false,
      "lastName": "Penge",
      "playerId": "51003",
      "position": "T36",
      "roundComplete": false,
      "rounds": [
        {
          "courseId": "014",
          "courseName": "Augusta National Golf Club",
          "roundId": 1,
          "scoreToPar": "+4",
          "strokes": 76
        },
        {
          "courseId": "014",
          "courseName": "Augusta National Golf Club",
          "roundId": 2,
          "scoreToPar": "-3",
          "strokes": 69
        },
        {
          "courseId": "014",
          "courseName": "Augusta National Golf Club",
          "roundId": 3,
          "scoreToPar": "-1",
          "strokes": 71
        }
      ],
      "startingHole": 1,
      "status": "not started",
      "teeTime": "10:45am",
      "teeTimeTimestamp": "2026-04-12T14:45:00",
      "thru": "",
      "total": "E",
      "totalStrokesFromCompletedRounds": "216"
    },
    {
      "courseId": "014",
      "currentHole": 1,
      "currentRound": 4,
      "currentRoundScore": "",
      "firstName": "Alex",
      "isAmateur": false,
      "lastName": "Noren",
      "playerId": "27349",
      "position": "T39",
      "roundComplete": false,
      "rounds": [
        {
          "courseId": "014",
          "courseName": "Augusta National Golf Club",
          "roundId": 1,
          "scoreToPar": "+5",
          "strokes": 77
        },
        {
          "courseId": "014",
          "courseName": "Augusta National Golf Club",
          "roundId": 2,
          "scoreToPar": "-1",
          "strokes": 71
        },
        {
          "courseId": "014",
          "courseName": "Augusta National Golf Club",
          "roundId": 3,
          "scoreToPar": "-3",
          "strokes": 69
        }
      ],
      "startingHole": 1,
      "status": "not started",
      "teeTime": "10:23am",
      "teeTimeTimestamp": "2026-04-12T14:23:00",
      "thru": "",
      "total": "+1",
      "totalStrokesFromCompletedRounds": "217"
    },
    {
      "courseId": "014",
      "currentHole": 1,
      "currentRound": 4,
      "currentRoundScore": "",
      "firstName": "Maverick",
      "isAmateur": false,
      "lastName": "McNealy",
      "playerId": "46442",
      "position": "T39",
      "roundComplete": false,
      "rounds": [
        {
          "courseId": "014",
          "courseName": "Augusta National Golf Club",
          "roundId": 1,
          "scoreToPar": "+5",
          "strokes": 77
        },
        {
          "courseId": "014",
          "courseName": "Augusta National Golf Club",
          "roundId": 2,
          "scoreToPar": "-2",
          "strokes": 70
        },
        {
          "courseId": "014",
          "courseName": "Augusta National Golf Club",
          "roundId": 3,
          "scoreToPar": "-2",
          "strokes": 70
        }
      ],
      "startingHole": 1,
      "status": "not started",
      "teeTime": "10:23am",
      "teeTimeTimestamp": "2026-04-12T14:23:00",
      "thru": "",
      "total": "+1",
      "totalStrokesFromCompletedRounds": "217"
    },
    {
      "courseId": "014",
      "currentHole": 1,
      "currentRound": 4,
      "currentRoundScore": "",
      "firstName": "Viktor",
      "isAmateur": false,
      "lastName": "Hovland",
      "playerId": "46717",
      "position": "T39",
      "roundComplete": false,
      "rounds": [
        {
          "courseId": "014",
          "courseName": "Augusta National Golf Club",
          "roundId": 1,
          "scoreToPar": "+3",
          "strokes": 75
        },
        {
          "courseId": "014",
          "courseName": "Augusta National Golf Club",
          "roundId": 2,
          "scoreToPar": "-1",
          "strokes": 71
        },
        {
          "courseId": "014",
          "courseName": "Augusta National Golf Club",
          "roundId": 3,
          "scoreToPar": "-1",
          "strokes": 71
        }
      ],
      "startingHole": 1,
      "status": "not started",
      "teeTime": "10:12am",
      "teeTimeTimestamp": "2026-04-12T14:12:00",
      "thru": "",
      "total": "+1",
      "totalStrokesFromCompletedRounds": "217"
    },
    {
      "courseId": "014",
      "currentHole": 1,
      "currentRound": 4,
      "currentRoundScore": "",
      "firstName": "Justin",
      "isAmateur": false,
      "lastName": "Thomas",
      "playerId": "33448",
      "position": "T39",
      "roundComplete": false,
      "rounds": [
        {
          "courseId": "014",
          "courseName": "Augusta National Golf Club",
          "roundId": 1,
          "scoreToPar": "E",
          "strokes": 72
        },
        {
          "courseId": "014",
          "courseName": "Augusta National Golf Club",
          "roundId": 2,
          "scoreToPar": "+2",
          "strokes": 74
        },
        {
          "courseId": "014",
          "courseName": "Augusta National Golf Club",
          "roundId": 3,
          "scoreToPar": "-1",
          "strokes": 71
        }
      ],
      "startingHole": 1,
      "status": "not started",
      "teeTime": "10:12am",
      "teeTimeTimestamp": "2026-04-12T14:12:00",
      "thru": "",
      "total": "+1",
      "totalStrokesFromCompletedRounds": "217"
    },
    {
      "courseId": "014",
      "currentHole": 1,
      "currentRound": 4,
      "currentRoundScore": "",
      "firstName": "Matt",
      "isAmateur": false,
      "lastName": "McCarty",
      "playerId": "59141",
      "position": "T39",
      "roundComplete": false,
      "rounds": [
        {
          "courseId": "014",
          "courseName": "Augusta National Golf Club",
          "roundId": 1,
          "scoreToPar": "E",
          "strokes": 72
        },
        {
          "courseId": "014",
          "courseName": "Augusta National Golf Club",
          "roundId": 2,
          "scoreToPar": "+1",
          "strokes": 73
        },
        {
          "courseId": "014",
          "courseName": "Augusta National Golf Club",
          "roundId": 3,
          "scoreToPar": "E",
          "strokes": 72
        }
      ],
      "startingHole": 1,
      "status": "active",
      "teeTime": "10:01am",
      "teeTimeTimestamp": "2026-04-12T14:01:00",
      "thru": "",
      "total": "+1",
      "totalStrokesFromCompletedRounds": "217"
    },
    {
      "courseId": "014",
      "currentHole": 2,
      "currentRound": 4,
      "currentRoundScore": "-1",
      "firstName": "Si Woo",
      "isAmateur": false,
      "lastName": "Kim",
      "playerId": "37455",
      "position": "T44",
      "roundComplete": false,
      "rounds": [
        {
          "courseId": "014",
          "courseName": "Augusta National Golf Club",
          "roundId": 1,
          "scoreToPar": "+3",
          "strokes": 75
        },
        {
          "courseId": "014",
          "courseName": "Augusta National Golf Club",
          "roundId": 2,
          "scoreToPar": "+1",
          "strokes": 73
        },
        {
          "courseId": "014",
          "courseName": "Augusta National Golf Club",
          "roundId": 3,
          "scoreToPar": "E",
          "strokes": 72
        }
      ],
      "startingHole": 1,
      "status": "active",
      "teeTime": "9:39am",
      "teeTimeTimestamp": "2026-04-12T13:39:00",
      "thru": "1",
      "total": "+3",
      "totalStrokesFromCompletedRounds": "220"
    },
    {
      "courseId": "014",
      "currentHole": 2,
      "currentRound": 4,
      "currentRoundScore": "E",
      "firstName": "Keegan",
      "isAmateur": false,
      "lastName": "Bradley",
      "playerId": "33141",
      "position": "T44",
      "roundComplete": false,
      "rounds": [
        {
          "courseId": "014",
          "courseName": "Augusta National Golf Club",
          "roundId": 1,
          "scoreToPar": "E",
          "strokes": 72
        },
        {
          "courseId": "014",
          "courseName": "Augusta National Golf Club",
          "roundId": 2,
          "scoreToPar": "+2",
          "strokes": 74
        },
        {
          "courseId": "014",
          "courseName": "Augusta National Golf Club",
          "roundId": 3,
          "scoreToPar": "+1",
          "strokes": 73
        }
      ],
      "startingHole": 1,
      "status": "active",
      "teeTime": "9:50am",
      "teeTimeTimestamp": "2026-04-12T13:50:00",
      "thru": "1",
      "total": "+3",
      "totalStrokesFromCompletedRounds": "219"
    },
    {
      "courseId": "014",
      "currentHole": 2,
      "currentRound": 4,
      "currentRoundScore": "E",
      "firstName": "Dustin",
      "isAmateur": false,
      "lastName": "Johnson",
      "playerId": "30925",
      "position": "T44",
      "roundComplete": false,
      "rounds": [
        {
          "courseId": "014",
          "courseName": "Augusta National Golf Club",
          "roundId": 1,
          "scoreToPar": "+1",
          "strokes": 73
        },
        {
          "courseId": "014",
          "courseName": "Augusta National Golf Club",
          "roundId": 2,
          "scoreToPar": "-1",
          "strokes": 71
        },
        {
          "courseId": "014",
          "courseName": "Augusta National Golf Club",
          "roundId": 3,
          "scoreToPar": "+3",
          "strokes": 75
        }
      ],
      "startingHole": 1,
      "status": "active",
      "teeTime": "9:50am",
      "teeTimeTimestamp": "2026-04-12T13:50:00",
      "thru": "1",
      "total": "+3",
      "totalStrokesFromCompletedRounds": "219"
    },
    {
      "courseId": "014",
      "currentHole": 1,
      "currentRound": 4,
      "currentRoundScore": "",
      "firstName": "Corey",
      "isAmateur": false,
      "lastName": "Conners",
      "playerId": "39997",
      "position": "T44",
      "roundComplete": false,
      "rounds": [
        {
          "courseId": "014",
          "courseName": "Augusta National Golf Club",
          "roundId": 1,
          "scoreToPar": "+3",
          "strokes": 75
        },
        {
          "courseId": "014",
          "courseName": "Augusta National Golf Club",
          "roundId": 2,
          "scoreToPar": "+1",
          "strokes": 73
        },
        {
          "courseId": "014",
          "courseName": "Augusta National Golf Club",
          "roundId": 3,
          "scoreToPar": "-1",
          "strokes": 71
        }
      ],
      "startingHole": 1,
      "status": "active",
      "teeTime": "10:01am",
      "teeTimeTimestamp": "2026-04-12T14:01:00",
      "thru": "",
      "total": "+3",
      "totalStrokesFromCompletedRounds": "219"
    },
    {
      "courseId": "014",
      "currentHole": 3,
      "currentRound": 4,
      "currentRoundScore": "-1",
      "firstName": "Jon",
      "isAmateur": false,
      "lastName": "Rahm",
      "playerId": "46970",
      "position": "48",
      "roundComplete": false,
      "rounds": [
        {
          "courseId": "014",
          "courseName": "Augusta National Golf Club",
          "roundId": 1,
          "scoreToPar": "+6",
          "strokes": 78
        },
        {
          "courseId": "014",
          "courseName": "Augusta National Golf Club",
          "roundId": 2,
          "scoreToPar": "-2",
          "strokes": 70
        },
        {
          "courseId": "014",
          "courseName": "Augusta National Golf Club",
          "roundId": 3,
          "scoreToPar": "+1",
          "strokes": 73
        }
      ],
      "startingHole": 1,
      "status": "active",
      "teeTime": "9:28am",
      "teeTimeTimestamp": "2026-04-12T13:28:00",
      "thru": "2",
      "total": "+4",
      "totalStrokesFromCompletedRounds": "221"
    },
    {
      "courseId": "014",
      "currentHole": 4,
      "currentRound": 4,
      "currentRoundScore": "-1",
      "firstName": "Gary",
      "isAmateur": false,
      "lastName": "Woodland",
      "playerId": "31323",
      "position": "49",
      "roundComplete": false,
      "rounds": [
        {
          "courseId": "014",
          "courseName": "Augusta National Golf Club",
          "roundId": 1,
          "scoreToPar": "-1",
          "strokes": 71
        },
        {
          "courseId": "014",
          "courseName": "Augusta National Golf Club",
          "roundId": 2,
          "scoreToPar": "+3",
          "strokes": 75
        },
        {
          "courseId": "014",
          "courseName": "Augusta National Golf Club",
          "roundId": 3,
          "scoreToPar": "+4",
          "strokes": 76
        }
      ],
      "startingHole": 1,
      "status": "active",
      "teeTime": "9:17am",
      "teeTimeTimestamp": "2026-04-12T13:17:00",
      "thru": "3",
      "total": "+5",
      "totalStrokesFromCompletedRounds": "222"
    },
    {
      "courseId": "014",
      "currentHole": 4,
      "currentRound": 4,
      "currentRoundScore": "-1",
      "firstName": "Kurt",
      "isAmateur": false,
      "lastName": "Kitayama",
      "playerId": "48117",
      "position": "T50",
      "roundComplete": false,
      "rounds": [
        {
          "courseId": "014",
          "courseName": "Augusta National Golf Club",
          "roundId": 1,
          "scoreToPar": "-3",
          "strokes": 69
        },
        {
          "courseId": "014",
          "courseName": "Augusta National Golf Club",
          "roundId": 2,
          "scoreToPar": "+7",
          "strokes": 79
        },
        {
          "courseId": "014",
          "courseName": "Augusta National Golf Club",
          "roundId": 3,
          "scoreToPar": "+3",
          "strokes": 75
        }
      ],
      "startingHole": 1,
      "status": "active",
      "teeTime": "9:17am",
      "teeTimeTimestamp": "2026-04-12T13:17:00",
      "thru": "3",
      "total": "+6",
      "totalStrokesFromCompletedRounds": "223"
    },
    {
      "courseId": "014",
      "currentHole": 3,
      "currentRound": 4,
      "currentRoundScore": "+1",
      "firstName": "Sergio",
      "isAmateur": false,
      "lastName": "Garcia",
      "playerId": "21209",
      "position": "T50",
      "roundComplete": false,
      "rounds": [
        {
          "courseId": "014",
          "courseName": "Augusta National Golf Club",
          "roundId": 1,
          "scoreToPar": "E",
          "strokes": 72
        },
        {
          "courseId": "014",
          "courseName": "Augusta National Golf Club",
          "roundId": 2,
          "scoreToPar": "+3",
          "strokes": 75
        },
        {
          "courseId": "014",
          "courseName": "Augusta National Golf Club",
          "roundId": 3,
          "scoreToPar": "+2",
          "strokes": 74
        }
      ],
      "startingHole": 1,
      "status": "active",
      "teeTime": "9:28am",
      "teeTimeTimestamp": "2026-04-12T13:28:00",
      "thru": "2",
      "total": "+6",
      "totalStrokesFromCompletedRounds": "221"
    },
    {
      "courseId": "014",
      "currentHole": 2,
      "currentRound": 4,
      "currentRoundScore": "+1",
      "firstName": "Rasmus",
      "isAmateur": false,
      "lastName": "Højgaard",
      "playerId": "52686",
      "position": "T50",
      "roundComplete": false,
      "rounds": [
        {
          "courseId": "014",
          "courseName": "Augusta National Golf Club",
          "roundId": 1,
          "scoreToPar": "+6",
          "strokes": 78
        },
        {
          "courseId": "014",
          "courseName": "Augusta National Golf Club",
          "roundId": 2,
          "scoreToPar": "-2",
          "strokes": 70
        },
        {
          "courseId": "014",
          "courseName": "Augusta National Golf Club",
          "roundId": 3,
          "scoreToPar": "+1",
          "strokes": 73
        }
      ],
      "startingHole": 1,
      "status": "active",
      "teeTime": "9:39am",
      "teeTimeTimestamp": "2026-04-12T13:39:00",
      "thru": "1",
      "total": "+6",
      "totalStrokesFromCompletedRounds": "221"
    },
    {
      "courseId": "014",
      "currentHole": 5,
      "currentRound": 4,
      "currentRoundScore": "+1",
      "firstName": "Aaron",
      "isAmateur": false,
      "lastName": "Rai",
      "playerId": "46414",
      "position": "53",
      "roundComplete": false,
      "rounds": [
        {
          "courseId": "014",
          "courseName": "Augusta National Golf Club",
          "roundId": 1,
          "scoreToPar": "-1",
          "strokes": 71
        },
        {
          "courseId": "014",
          "courseName": "Augusta National Golf Club",
          "roundId": 2,
          "scoreToPar": "+2",
          "strokes": 74
        },
        {
          "courseId": "014",
          "courseName": "Augusta National Golf Club",
          "roundId": 3,
          "scoreToPar": "+6",
          "strokes": 78
        }
      ],
      "startingHole": 1,
      "status": "active",
      "teeTime": "9:06am",
      "teeTimeTimestamp": "2026-04-12T13:06:00",
      "thru": "4",
      "total": "+8",
      "totalStrokesFromCompletedRounds": "223"
    },
    {
      "courseId": "014",
      "currentHole": 5,
      "currentRound": 4,
      "currentRoundScore": "+4",
      "firstName": "Charl",
      "isAmateur": false,
      "lastName": "Schwartzel",
      "playerId": "26331",
      "position": "54",
      "roundComplete": false,
      "rounds": [
        {
          "courseId": "014",
          "courseName": "Augusta National Golf Club",
          "roundId": 1,
          "scoreToPar": "+3",
          "strokes": 75
        },
        {
          "courseId": "014",
          "courseName": "Augusta National Golf Club",
          "roundId": 2,
          "scoreToPar": "+1",
          "strokes": 73
        },
        {
          "courseId": "014",
          "courseName": "Augusta National Golf Club",
          "roundId": 3,
          "scoreToPar": "+5",
          "strokes": 77
        }
      ],
      "startingHole": 1,
      "status": "active",
      "teeTime": "9:06am",
      "teeTimeTimestamp": "2026-04-12T13:06:00",
      "thru": "4",
      "total": "+13",
      "totalStrokesFromCompletedRounds": "225"
    },
    {
      "courseId": "014",
      "currentHole": 1,
      "currentRound": 2,
      "currentRoundScore": "",
      "firstName": "Danny",
      "isAmateur": false,
      "lastName": "Willett",
      "playerId": "32139",
      "position": "CUT",
      "roundComplete": false,
      "rounds": [
        {
          "courseId": "014",
          "courseName": "Augusta National Golf Club",
          "roundId": 1,
          "scoreToPar": "+4",
          "strokes": 76
        },
        {
          "courseId": "014",
          "courseName": "Augusta National Golf Club",
          "roundId": 2,
          "scoreToPar": "+1",
          "strokes": 73
        }
      ],
      "startingHole": 1,
      "status": "cut",
      "thru": "",
      "total": "+5",
      "totalStrokesFromCompletedRounds": "149"
    },
    {
      "courseId": "014",
      "currentHole": 1,
      "currentRound": 2,
      "currentRoundScore": "",
      "firstName": "Harry",
      "isAmateur": false,
      "lastName": "Hall",
      "playerId": "57975",
      "position": "CUT",
      "roundComplete": false,
      "rounds": [
        {
          "courseId": "014",
          "courseName": "Augusta National Golf Club",
          "roundId": 1,
          "scoreToPar": "+5",
          "strokes": 77
        },
        {
          "courseId": "014",
          "courseName": "Augusta National Golf Club",
          "roundId": 2,
          "scoreToPar": "E",
          "strokes": 72
        }
      ],
      "startingHole": 1,
      "status": "cut",
      "thru": "",
      "total": "+5",
      "totalStrokesFromCompletedRounds": "149"
    },
    {
      "courseId": "014",
      "currentHole": 1,
      "currentRound": 2,
      "currentRoundScore": "",
      "firstName": "J.J.",
      "isAmateur": false,
      "lastName": "Spaun",
      "playerId": "39324",
      "position": "CUT",
      "roundComplete": false,
      "rounds": [
        {
          "courseId": "014",
          "courseName": "Augusta National Golf Club",
          "roundId": 1,
          "scoreToPar": "+2",
          "strokes": 74
        },
        {
          "courseId": "014",
          "courseName": "Augusta National Golf Club",
          "roundId": 2,
          "scoreToPar": "+3",
          "strokes": 75
        }
      ],
      "startingHole": 1,
      "status": "cut",
      "thru": "",
      "total": "+5",
      "totalStrokesFromCompletedRounds": "149"
    },
    {
      "courseId": "014",
      "currentHole": 1,
      "currentRound": 2,
      "currentRoundScore": "",
      "firstName": "Ryan",
      "isAmateur": false,
      "lastName": "Fox",
      "playerId": "29936",
      "position": "CUT",
      "roundComplete": false,
      "rounds": [
        {
          "courseId": "014",
          "courseName": "Augusta National Golf Club",
          "roundId": 1,
          "scoreToPar": "+5",
          "strokes": 77
        },
        {
          "courseId": "014",
          "courseName": "Augusta National Golf Club",
          "roundId": 2,
          "scoreToPar": "E",
          "strokes": 72
        }
      ],
      "startingHole": 1,
      "status": "cut",
      "thru": "",
      "total": "+5",
      "totalStrokesFromCompletedRounds": "149"
    },
    {
      "courseId": "014",
      "currentHole": 1,
      "currentRound": 2,
      "currentRoundScore": "",
      "firstName": "Bubba",
      "isAmateur": false,
      "lastName": "Watson",
      "playerId": "25804",
      "position": "CUT",
      "roundComplete": false,
      "rounds": [
        {
          "courseId": "014",
          "courseName": "Augusta National Golf Club",
          "roundId": 1,
          "scoreToPar": "+4",
          "strokes": 76
        },
        {
          "courseId": "014",
          "courseName": "Augusta National Golf Club",
          "roundId": 2,
          "scoreToPar": "+1",
          "strokes": 73
        }
      ],
      "startingHole": 1,
      "status": "cut",
      "thru": "",
      "total": "+5",
      "totalStrokesFromCompletedRounds": "149"
    },
    {
      "courseId": "014",
      "currentHole": 1,
      "currentRound": 2,
      "currentRoundScore": "",
      "firstName": "Zach",
      "isAmateur": false,
      "lastName": "Johnson",
      "playerId": "24024",
      "position": "CUT",
      "roundComplete": false,
      "rounds": [
        {
          "courseId": "014",
          "courseName": "Augusta National Golf Club",
          "roundId": 1,
          "scoreToPar": "+3",
          "strokes": 75
        },
        {
          "courseId": "014",
          "courseName": "Augusta National Golf Club",
          "roundId": 2,
          "scoreToPar": "+3",
          "strokes": 75
        }
      ],
      "startingHole": 1,
      "status": "cut",
      "thru": "",
      "total": "+6",
      "totalStrokesFromCompletedRounds": "150"
    },
    {
      "courseId": "014",
      "currentHole": 1,
      "currentRound": 2,
      "currentRoundScore": "",
      "firstName": "Nicolai",
      "isAmateur": false,
      "lastName": "Højgaard",
      "playerId": "52453",
      "position": "CUT",
      "roundComplete": false,
      "rounds": [
        {
          "courseId": "014",
          "courseName": "Augusta National Golf Club",
          "roundId": 1,
          "scoreToPar": "+4",
          "strokes": 76
        },
        {
          "courseId": "014",
          "courseName": "Augusta National Golf Club",
          "roundId": 2,
          "scoreToPar": "+2",
          "strokes": 74
        }
      ],
      "startingHole": 1,
      "status": "cut",
      "thru": "",
      "total": "+6",
      "totalStrokesFromCompletedRounds": "150"
    },
    {
      "courseId": "014",
      "currentHole": 1,
      "currentRound": 2,
      "currentRoundScore": "",
      "firstName": "Akshay",
      "isAmateur": false,
      "lastName": "Bhatia",
      "playerId": "56630",
      "position": "CUT",
      "roundComplete": false,
      "rounds": [
        {
          "courseId": "014",
          "courseName": "Augusta National Golf Club",
          "roundId": 1,
          "scoreToPar": "+1",
          "strokes": 73
        },
        {
          "courseId": "014",
          "courseName": "Augusta National Golf Club",
          "roundId": 2,
          "scoreToPar": "+5",
          "strokes": 77
        }
      ],
      "startingHole": 1,
      "status": "cut",
      "thru": "",
      "total": "+6",
      "totalStrokesFromCompletedRounds": "150"
    },
    {
      "courseId": "014",
      "currentHole": 1,
      "currentRound": 2,
      "currentRoundScore": "",
      "firstName": "Bryson",
      "isAmateur": false,
      "lastName": "DeChambeau",
      "playerId": "47959",
      "position": "CUT",
      "roundComplete": false,
      "rounds": [
        {
          "courseId": "014",
          "courseName": "Augusta National Golf Club",
          "roundId": 1,
          "scoreToPar": "+4",
          "strokes": 76
        },
        {
          "courseId": "014",
          "courseName": "Augusta National Golf Club",
          "roundId": 2,
          "scoreToPar": "+2",
          "strokes": 74
        }
      ],
      "startingHole": 1,
      "status": "cut",
      "thru": "",
      "total": "+6",
      "totalStrokesFromCompletedRounds": "150"
    },
    {
      "courseId": "014",
      "currentHole": 1,
      "currentRound": 2,
      "currentRoundScore": "",
      "firstName": "Andrew",
      "isAmateur": false,
      "lastName": "Novak",
      "playerId": "51997",
      "position": "CUT",
      "roundComplete": false,
      "rounds": [
        {
          "courseId": "014",
          "courseName": "Augusta National Golf Club",
          "roundId": 1,
          "scoreToPar": "+3",
          "strokes": 75
        },
        {
          "courseId": "014",
          "courseName": "Augusta National Golf Club",
          "roundId": 2,
          "scoreToPar": "+4",
          "strokes": 76
        }
      ],
      "startingHole": 1,
      "status": "cut",
      "thru": "",
      "total": "+7",
      "totalStrokesFromCompletedRounds": "151"
    },
    {
      "courseId": "014",
      "currentHole": 1,
      "currentRound": 2,
      "currentRoundScore": "",
      "firstName": "Tom",
      "isAmateur": false,
      "lastName": "McKibbin",
      "playerId": "50823",
      "position": "CUT",
      "roundComplete": false,
      "rounds": [
        {
          "courseId": "014",
          "courseName": "Augusta National Golf Club",
          "roundId": 1,
          "scoreToPar": "+3",
          "strokes": 75
        },
        {
          "courseId": "014",
          "courseName": "Augusta National Golf Club",
          "roundId": 2,
          "scoreToPar": "+4",
          "strokes": 76
        }
      ],
      "startingHole": 1,
      "status": "cut",
      "thru": "",
      "total": "+7",
      "totalStrokesFromCompletedRounds": "151"
    },
    {
      "courseId": "014",
      "currentHole": 1,
      "currentRound": 2,
      "currentRoundScore": "",
      "firstName": "Robert",
      "isAmateur": false,
      "lastName": "MacIntyre",
      "playerId": "52215",
      "position": "CUT",
      "roundComplete": false,
      "rounds": [
        {
          "courseId": "014",
          "courseName": "Augusta National Golf Club",
          "roundId": 1,
          "scoreToPar": "+8",
          "strokes": 80
        },
        {
          "courseId": "014",
          "courseName": "Augusta National Golf Club",
          "roundId": 2,
          "scoreToPar": "-1",
          "strokes": 71
        }
      ],
      "startingHole": 1,
      "status": "cut",
      "thru": "",
      "total": "+7",
      "totalStrokesFromCompletedRounds": "151"
    },
    {
      "courseId": "014",
      "currentHole": 1,
      "currentRound": 2,
      "currentRoundScore": "",
      "firstName": "Rasmus",
      "isAmateur": false,
      "lastName": "Neergaard-Petersen",
      "playerId": "52689",
      "position": "CUT",
      "roundComplete": false,
      "rounds": [
        {
          "courseId": "014",
          "courseName": "Augusta National Golf Club",
          "roundId": 1,
          "scoreToPar": "+5",
          "strokes": 77
        },
        {
          "courseId": "014",
          "courseName": "Augusta National Golf Club",
          "roundId": 2,
          "scoreToPar": "+2",
          "strokes": 74
        }
      ],
      "startingHole": 1,
      "status": "cut",
      "thru": "",
      "total": "+7",
      "totalStrokesFromCompletedRounds": "151"
    },
    {
      "courseId": "014",
      "currentHole": 1,
      "currentRound": 2,
      "currentRoundScore": "",
      "firstName": "Cameron",
      "isAmateur": false,
      "lastName": "Smith",
      "playerId": "35891",
      "position": "CUT",
      "roundComplete": false,
      "rounds": [
        {
          "courseId": "014",
          "courseName": "Augusta National Golf Club",
          "roundId": 1,
          "scoreToPar": "+2",
          "strokes": 74
        },
        {
          "courseId": "014",
          "courseName": "Augusta National Golf Club",
          "roundId": 2,
          "scoreToPar": "+5",
          "strokes": 77
        }
      ],
      "startingHole": 1,
      "status": "cut",
      "thru": "",
      "total": "+7",
      "totalStrokesFromCompletedRounds": "151"
    },
    {
      "courseId": "014",
      "currentHole": 1,
      "currentRound": 2,
      "currentRoundScore": "",
      "firstName": "Michael",
      "isAmateur": false,
      "lastName": "Kim",
      "playerId": "39975",
      "position": "CUT",
      "roundComplete": false,
      "rounds": [
        {
          "courseId": "014",
          "courseName": "Augusta National Golf Club",
          "roundId": 1,
          "scoreToPar": "+3",
          "strokes": 75
        },
        {
          "courseId": "014",
          "courseName": "Augusta National Golf Club",
          "roundId": 2,
          "scoreToPar": "+5",
          "strokes": 77
        }
      ],
      "startingHole": 1,
      "status": "cut",
      "thru": "",
      "total": "+8",
      "totalStrokesFromCompletedRounds": "152"
    },
    {
      "courseId": "014",
      "currentHole": 1,
      "currentRound": 2,
      "currentRoundScore": "",
      "firstName": "Ethan",
      "isAmateur": true,
      "lastName": "Fang",
      "playerId": "68932",
      "position": "CUT",
      "roundComplete": false,
      "rounds": [
        {
          "courseId": "014",
          "courseName": "Augusta National Golf Club",
          "roundId": 1,
          "scoreToPar": "+2",
          "strokes": 74
        },
        {
          "courseId": "014",
          "courseName": "Augusta National Golf Club",
          "roundId": 2,
          "scoreToPar": "+6",
          "strokes": 78
        }
      ],
      "startingHole": 1,
      "status": "cut",
      "thru": "",
      "total": "+8",
      "totalStrokesFromCompletedRounds": "152"
    },
    {
      "courseId": "014",
      "currentHole": 1,
      "currentRound": 2,
      "currentRoundScore": "",
      "firstName": "Daniel",
      "isAmateur": false,
      "lastName": "Berger",
      "playerId": "40026",
      "position": "CUT",
      "roundComplete": false,
      "rounds": [
        {
          "courseId": "014",
          "courseName": "Augusta National Golf Club",
          "roundId": 1,
          "scoreToPar": "+4",
          "strokes": 76
        },
        {
          "courseId": "014",
          "courseName": "Augusta National Golf Club",
          "roundId": 2,
          "scoreToPar": "+4",
          "strokes": 76
        }
      ],
      "startingHole": 1,
      "status": "cut",
      "thru": "",
      "total": "+8",
      "totalStrokesFromCompletedRounds": "152"
    },
    {
      "courseId": "014",
      "currentHole": 1,
      "currentRound": 2,
      "currentRoundScore": "",
      "firstName": "Jackson",
      "isAmateur": true,
      "lastName": "Herrington",
      "playerId": "70148",
      "position": "CUT",
      "roundComplete": false,
      "rounds": [
        {
          "courseId": "014",
          "courseName": "Augusta National Golf Club",
          "roundId": 1,
          "scoreToPar": "+4",
          "strokes": 76
        },
        {
          "courseId": "014",
          "courseName": "Augusta National Golf Club",
          "roundId": 2,
          "scoreToPar": "+4",
          "strokes": 76
        }
      ],
      "startingHole": 1,
      "status": "cut",
      "thru": "",
      "total": "+8",
      "totalStrokesFromCompletedRounds": "152"
    },
    {
      "courseId": "014",
      "currentHole": 1,
      "currentRound": 2,
      "currentRoundScore": "",
      "firstName": "Casey",
      "isAmateur": false,
      "lastName": "Jarvis",
      "playerId": "57688",
      "position": "CUT",
      "roundComplete": false,
      "rounds": [
        {
          "courseId": "014",
          "courseName": "Augusta National Golf Club",
          "roundId": 1,
          "scoreToPar": "+5",
          "strokes": 77
        },
        {
          "courseId": "014",
          "courseName": "Augusta National Golf Club",
          "roundId": 2,
          "scoreToPar": "+3",
          "strokes": 75
        }
      ],
      "startingHole": 1,
      "status": "cut",
      "thru": "",
      "total": "+8",
      "totalStrokesFromCompletedRounds": "152"
    },
    {
      "courseId": "014",
      "currentHole": 1,
      "currentRound": 2,
      "currentRoundScore": "",
      "firstName": "Fred",
      "isAmateur": false,
      "lastName": "Couples",
      "playerId": "01226",
      "position": "CUT",
      "roundComplete": false,
      "rounds": [
        {
          "courseId": "014",
          "courseName": "Augusta National Golf Club",
          "roundId": 1,
          "scoreToPar": "+6",
          "strokes": 78
        },
        {
          "courseId": "014",
          "courseName": "Augusta National Golf Club",
          "roundId": 2,
          "scoreToPar": "+3",
          "strokes": 75
        }
      ],
      "startingHole": 1,
      "status": "cut",
      "thru": "",
      "total": "+9",
      "totalStrokesFromCompletedRounds": "153"
    },
    {
      "courseId": "014",
      "currentHole": 1,
      "currentRound": 2,
      "currentRoundScore": "",
      "firstName": "José María",
      "isAmateur": false,
      "lastName": "Olazábal",
      "playerId": "06373",
      "position": "CUT",
      "roundComplete": false,
      "rounds": [
        {
          "courseId": "014",
          "courseName": "Augusta National Golf Club",
          "roundId": 1,
          "scoreToPar": "+2",
          "strokes": 74
        },
        {
          "courseId": "014",
          "courseName": "Augusta National Golf Club",
          "roundId": 2,
          "scoreToPar": "+7",
          "strokes": 79
        }
      ],
      "startingHole": 1,
      "status": "cut",
      "thru": "",
      "total": "+9",
      "totalStrokesFromCompletedRounds": "153"
    },
    {
      "courseId": "014",
      "currentHole": 1,
      "currentRound": 2,
      "currentRoundScore": "",
      "firstName": "Mason",
      "isAmateur": true,
      "lastName": "Howell",
      "playerId": "68607",
      "position": "CUT",
      "roundComplete": false,
      "rounds": [
        {
          "courseId": "014",
          "courseName": "Augusta National Golf Club",
          "roundId": 1,
          "scoreToPar": "+5",
          "strokes": 77
        },
        {
          "courseId": "014",
          "courseName": "Augusta National Golf Club",
          "roundId": 2,
          "scoreToPar": "+4",
          "strokes": 76
        }
      ],
      "startingHole": 1,
      "status": "cut",
      "thru": "",
      "total": "+9",
      "totalStrokesFromCompletedRounds": "153"
    },
    {
      "courseId": "014",
      "currentHole": 1,
      "currentRound": 2,
      "currentRoundScore": "",
      "firstName": "Mike",
      "isAmateur": false,
      "lastName": "Weir",
      "playerId": "10423",
      "position": "CUT",
      "roundComplete": false,
      "rounds": [
        {
          "courseId": "014",
          "courseName": "Augusta National Golf Club",
          "roundId": 1,
          "scoreToPar": "+9",
          "strokes": 81
        },
        {
          "courseId": "014",
          "courseName": "Augusta National Golf Club",
          "roundId": 2,
          "scoreToPar": "+1",
          "strokes": 73
        }
      ],
      "startingHole": 1,
      "status": "cut",
      "thru": "",
      "total": "+10",
      "totalStrokesFromCompletedRounds": "154"
    },
    {
      "courseId": "014",
      "currentHole": 1,
      "currentRound": 2,
      "currentRoundScore": "",
      "firstName": "Vijay",
      "isAmateur": false,
      "lastName": "Singh",
      "playerId": "06567",
      "position": "CUT",
      "roundComplete": false,
      "rounds": [
        {
          "courseId": "014",
          "courseName": "Augusta National Golf Club",
          "roundId": 1,
          "scoreToPar": "+7",
          "strokes": 79
        },
        {
          "courseId": "014",
          "courseName": "Augusta National Golf Club",
          "roundId": 2,
          "scoreToPar": "+3",
          "strokes": 75
        }
      ],
      "startingHole": 1,
      "status": "cut",
      "thru": "",
      "total": "+10",
      "totalStrokesFromCompletedRounds": "154"
    },
    {
      "courseId": "014",
      "currentHole": 1,
      "currentRound": 2,
      "currentRoundScore": "",
      "firstName": "Min Woo",
      "isAmateur": false,
      "lastName": "Lee",
      "playerId": "37378",
      "position": "CUT",
      "roundComplete": false,
      "rounds": [
        {
          "courseId": "014",
          "courseName": "Augusta National Golf Club",
          "roundId": 1,
          "scoreToPar": "+6",
          "strokes": 78
        },
        {
          "courseId": "014",
          "courseName": "Augusta National Golf Club",
          "roundId": 2,
          "scoreToPar": "+5",
          "strokes": 77
        }
      ],
      "startingHole": 1,
      "status": "cut",
      "thru": "",
      "total": "+11",
      "totalStrokesFromCompletedRounds": "155"
    },
    {
      "courseId": "014",
      "currentHole": 1,
      "currentRound": 2,
      "currentRoundScore": "",
      "firstName": "Fifa",
      "isAmateur": true,
      "lastName": "Laopakdee",
      "playerId": "70146",
      "position": "CUT",
      "roundComplete": false,
      "rounds": [
        {
          "courseId": "014",
          "courseName": "Augusta National Golf Club",
          "roundId": 1,
          "scoreToPar": "+8",
          "strokes": 80
        },
        {
          "courseId": "014",
          "courseName": "Augusta National Golf Club",
          "roundId": 2,
          "scoreToPar": "+3",
          "strokes": 75
        }
      ],
      "startingHole": 1,
      "status": "cut",
      "thru": "",
      "total": "+11",
      "totalStrokesFromCompletedRounds": "155"
    },
    {
      "courseId": "014",
      "currentHole": 1,
      "currentRound": 2,
      "currentRoundScore": "",
      "firstName": "John",
      "isAmateur": false,
      "lastName": "Keefer",
      "playerId": "63454",
      "position": "CUT",
      "roundComplete": false,
      "rounds": [
        {
          "courseId": "014",
          "courseName": "Augusta National Golf Club",
          "roundId": 1,
          "scoreToPar": "+4",
          "strokes": 76
        },
        {
          "courseId": "014",
          "courseName": "Augusta National Golf Club",
          "roundId": 2,
          "scoreToPar": "+7",
          "strokes": 79
        }
      ],
      "startingHole": 1,
      "status": "cut",
      "thru": "",
      "total": "+11",
      "totalStrokesFromCompletedRounds": "155"
    },
    {
      "courseId": "014",
      "currentHole": 1,
      "currentRound": 2,
      "currentRoundScore": "",
      "firstName": "Carlos",
      "isAmateur": false,
      "lastName": "Ortiz",
      "playerId": "33667",
      "position": "CUT",
      "roundComplete": false,
      "rounds": [
        {
          "courseId": "014",
          "courseName": "Augusta National Golf Club",
          "roundId": 1,
          "scoreToPar": "+8",
          "strokes": 80
        },
        {
          "courseId": "014",
          "courseName": "Augusta National Golf Club",
          "roundId": 2,
          "scoreToPar": "+3",
          "strokes": 75
        }
      ],
      "startingHole": 1,
      "status": "cut",
      "thru": "",
      "total": "+11",
      "totalStrokesFromCompletedRounds": "155"
    },
    {
      "courseId": "014",
      "currentHole": 1,
      "currentRound": 2,
      "currentRoundScore": "",
      "firstName": "Sami",
      "isAmateur": false,
      "lastName": "Valimaki",
      "playerId": "52666",
      "position": "CUT",
      "roundComplete": false,
      "rounds": [
        {
          "courseId": "014",
          "courseName": "Augusta National Golf Club",
          "roundId": 1,
          "scoreToPar": "+8",
          "strokes": 80
        },
        {
          "courseId": "014",
          "courseName": "Augusta National Golf Club",
          "roundId": 2,
          "scoreToPar": "+3",
          "strokes": 75
        }
      ],
      "startingHole": 1,
      "status": "cut",
      "thru": "",
      "total": "+11",
      "totalStrokesFromCompletedRounds": "155"
    },
    {
      "courseId": "014",
      "currentHole": 1,
      "currentRound": 2,
      "currentRoundScore": "",
      "firstName": "Max",
      "isAmateur": false,
      "lastName": "Greyserman",
      "playerId": "51977",
      "position": "CUT",
      "roundComplete": false,
      "rounds": [
        {
          "courseId": "014",
          "courseName": "Augusta National Golf Club",
          "roundId": 1,
          "scoreToPar": "+7",
          "strokes": 79
        },
        {
          "courseId": "014",
          "courseName": "Augusta National Golf Club",
          "roundId": 2,
          "scoreToPar": "+5",
          "strokes": 77
        }
      ],
      "startingHole": 1,
      "status": "cut",
      "thru": "",
      "total": "+12",
      "totalStrokesFromCompletedRounds": "156"
    },
    {
      "courseId": "014",
      "currentHole": 1,
      "currentRound": 2,
      "currentRoundScore": "",
      "firstName": "Nicolas",
      "isAmateur": false,
      "lastName": "Echavarria",
      "playerId": "51349",
      "position": "CUT",
      "roundComplete": false,
      "rounds": [
        {
          "courseId": "014",
          "courseName": "Augusta National Golf Club",
          "roundId": 1,
          "scoreToPar": "+7",
          "strokes": 79
        },
        {
          "courseId": "014",
          "courseName": "Augusta National Golf Club",
          "roundId": 2,
          "scoreToPar": "+6",
          "strokes": 78
        }
      ],
      "startingHole": 1,
      "status": "cut",
      "thru": "",
      "total": "+13",
      "totalStrokesFromCompletedRounds": "157"
    },
    {
      "courseId": "014",
      "currentHole": 1,
      "currentRound": 2,
      "currentRoundScore": "",
      "firstName": "Mateo",
      "isAmateur": true,
      "lastName": "Pulcini",
      "playerId": "70145",
      "position": "CUT",
      "roundComplete": false,
      "rounds": [
        {
          "courseId": "014",
          "courseName": "Augusta National Golf Club",
          "roundId": 1,
          "scoreToPar": "+9",
          "strokes": 81
        },
        {
          "courseId": "014",
          "courseName": "Augusta National Golf Club",
          "roundId": 2,
          "scoreToPar": "+6",
          "strokes": 78
        }
      ],
      "startingHole": 1,
      "status": "cut",
      "thru": "",
      "total": "+15",
      "totalStrokesFromCompletedRounds": "159"
    },
    {
      "courseId": "014",
      "currentHole": 1,
      "currentRound": 2,
      "currentRoundScore": "",
      "firstName": "Naoyuki",
      "isAmateur": false,
      "lastName": "Kataoka",
      "playerId": "46879",
      "position": "CUT",
      "roundComplete": false,
      "rounds": [
        {
          "courseId": "014",
          "courseName": "Augusta National Golf Club",
          "roundId": 1,
          "scoreToPar": "+12",
          "strokes": 84
        },
        {
          "courseId": "014",
          "courseName": "Augusta National Golf Club",
          "roundId": 2,
          "scoreToPar": "+3",
          "strokes": 75
        }
      ],
      "startingHole": 1,
      "status": "cut",
      "thru": "",
      "total": "+15",
      "totalStrokesFromCompletedRounds": "159"
    },
    {
      "courseId": "014",
      "currentHole": 1,
      "currentRound": 2,
      "currentRoundScore": "",
      "firstName": "Aldrich",
      "isAmateur": false,
      "lastName": "Potgieter",
      "playerId": "63343",
      "position": "CUT",
      "roundComplete": false,
      "rounds": [
        {
          "courseId": "014",
          "courseName": "Augusta National Golf Club",
          "roundId": 1,
          "scoreToPar": "+12",
          "strokes": 84
        },
        {
          "courseId": "014",
          "courseName": "Augusta National Golf Club",
          "roundId": 2,
          "scoreToPar": "+3",
          "strokes": 75
        }
      ],
      "startingHole": 1,
      "status": "cut",
      "thru": "",
      "total": "+15",
      "totalStrokesFromCompletedRounds": "159"
    },
    {
      "courseId": "014",
      "currentHole": 1,
      "currentRound": 2,
      "currentRoundScore": "",
      "firstName": "Brandon",
      "isAmateur": true,
      "lastName": "Holtz",
      "playerId": "70147",
      "position": "CUT",
      "roundComplete": false,
      "rounds": [
        {
          "courseId": "014",
          "courseName": "Augusta National Golf Club",
          "roundId": 1,
          "scoreToPar": "+9",
          "strokes": 81
        },
        {
          "courseId": "014",
          "courseName": "Augusta National Golf Club",
          "roundId": 2,
          "scoreToPar": "+6",
          "strokes": 78
        }
      ],
      "startingHole": 1,
      "status": "cut",
      "thru": "",
      "total": "+15",
      "totalStrokesFromCompletedRounds": "159"
    },
    {
      "courseId": "014",
      "currentHole": 1,
      "currentRound": 2,
      "currentRoundScore": "",
      "firstName": "Angel",
      "isAmateur": false,
      "lastName": "Cabrera",
      "playerId": "20848",
      "position": "CUT",
      "roundComplete": false,
      "rounds": [
        {
          "courseId": "014",
          "courseName": "Augusta National Golf Club",
          "roundId": 1,
          "scoreToPar": "+7",
          "strokes": 79
        },
        {
          "courseId": "014",
          "courseName": "Augusta National Golf Club",
          "roundId": 2,
          "scoreToPar": "+9",
          "strokes": 81
        }
      ],
      "startingHole": 1,
      "status": "cut",
      "thru": "",
      "total": "+16",
      "totalStrokesFromCompletedRounds": "160"
    },
    {
      "courseId": "014",
      "currentHole": 1,
      "currentRound": 2,
      "currentRoundScore": "",
      "firstName": "Davis",
      "isAmateur": false,
      "lastName": "Riley",
      "playerId": "47995",
      "position": "CUT",
      "roundComplete": false,
      "rounds": [
        {
          "courseId": "014",
          "courseName": "Augusta National Golf Club",
          "roundId": 1,
          "scoreToPar": "+10",
          "strokes": 82
        },
        {
          "courseId": "014",
          "courseName": "Augusta National Golf Club",
          "roundId": 2,
          "scoreToPar": "+8",
          "strokes": 80
        }
      ],
      "startingHole": 1,
      "status": "cut",
      "thru": "",
      "total": "+18",
      "totalStrokesFromCompletedRounds": "162"
    }
  ],
  "orgId": "1",
  "roundId": 4,
  "roundStatus": "In Progress",
  "status": "In Progress",
  "timestamp": "2026-04-12T14:07:32.808000",
  "tournId": "014",
  "year": "2026"
}
